ndplot.py
ndplot-1.0.5.dist-info/licenses/LICENSE
ndplot-1.0.5.dist-info/METADATA
ndplot-1.0.5.dist-info/WHEEL
ndplot-1.0.5.dist-info/entry_points.txt
ndplot-1.0.5.dist-info/top_level.txt
ndplot-1.0.5.dist-info/RECORD
