Metadata-Version: 2.4
Name: ndplot
Version: 1.0.5
Summary: A tool to perform n-dimensional plots from a collection of figures.
Author-email: Stefano Dal Forno <tenobaldi@gmail.com>
Maintainer-email: Stefano Dal Forno <tenobaldi@gmail.com>
License-Expression: GPL-3.0-or-later
Project-URL: Repository, https://github.com/me/ndplot.git
Project-URL: Funding, https://buymeacoffee.com/tentacolo
Keywords: plot,visualization,n dimensional,multi dimensional,sliders,interactive
Classifier: Development Status :: 5 - Production/Stable
Classifier: Programming Language :: Python
Requires-Python: >=3.12
License-File: LICENSE
Requires-Dist: matplotlib
Dynamic: license-file
